sanic_jwt_payload_encrypt/__init__.py
sanic_jwt_payload_encrypt/encrypt_auth.py
sanic_jwt_payload_encrypt-1.0.8.dist-info/METADATA
sanic_jwt_payload_encrypt-1.0.8.dist-info/WHEEL
sanic_jwt_payload_encrypt-1.0.8.dist-info/top_level.txt
sanic_jwt_payload_encrypt-1.0.8.dist-info/zip-safe
sanic_jwt_payload_encrypt-1.0.8.dist-info/RECORD
